{
  "project_info": {
    "project_number": "43290088318",
    "project_id": "android-firebase-e87a8",
    "storage_bucket": "android-firebase-e87a8.appspot.com"
  },
  "client": [
    {
      "client_info": {
        "mobilesdk_app_id": "1:43290088318:android:bd728ccfe04f792639592f",
        "android_client_info": {
          "package_name": "com.turquoise.hotelbookrecomendation"
        }
      },
      "oauth_client": [
        {
          "client_id": "43290088318-46ed7d7ibk8sdpjtjipbv6vmbmn0ifcl.apps.googleusercontent.com",
          "client_type": 3
        }
      ],
      "api_key": [
        {
          "current_key": "AIzaSyCjQD4qa6bY47w5FQKYxd3mp5nDfEV9o7A"
        }
      ],
      "services": {
        "appinvite_service": {
          "other_platform_oauth_client": [
            {
              "client_id": "43290088318-46ed7d7ibk8sdpjtjipbv6vmbmn0ifcl.apps.googleusercontent.com",
              "client_type": 3
            }
          ]
        }
      }
    }
  ],
  "configuration_version": "1"
}